nem/__init__.py
nem/importer.py
nem-0.1.dist-info/DESCRIPTION.rst
nem-0.1.dist-info/METADATA
nem-0.1.dist-info/RECORD
nem-0.1.dist-info/WHEEL
nem-0.1.dist-info/metadata.json
nem-0.1.dist-info/top_level.txt
