Metadata-Version: 2.0
Name: nem
Version: 0.1
Summary: Access library for AEMO / NEM goverement data
Home-page: https://github.com/theskorm/nemweb2
Author: Michael Wheeler
Author-email: michael@michael-wheeler.org
License: UNKNOWN
Download-URL: https://github.com/TheSkorm/nemweb2/archive/0.0.1.tar.gz
Keywords: aemo,nem,gov,au
Platform: UNKNOWN
Requires-Dist: beautifulsoup4
Requires-Dist: boto3
Requires-Dist: arrow
